ruamel.nss-0.1.5-py3.9-nspkg.pth
ruamel/nss/__init__.py
ruamel/nss/grp.py
ruamel/nss/pwd.py
ruamel/nss/spwd.py
ruamel.nss-0.1.5.dist-info/METADATA
ruamel.nss-0.1.5.dist-info/WHEEL
ruamel.nss-0.1.5.dist-info/namespace_packages.txt
ruamel.nss-0.1.5.dist-info/top_level.txt
ruamel.nss-0.1.5.dist-info/RECORD
