Metadata-Version: 2.1
Name: ruamel.nss
Version: 0.1.5
Summary: managing passwd, group and shadow under /etc, /usr/lib/extrausers, etc.
Home-page: https://sourceforge.net/p/ruamel-nss/code/ci/default/tree
Author: Anthon van der Neut
Author-email: a.van.der.neut@ruamel.eu
License: Copyright Ruamel bvba 2007-2016
Platform: UNKNOWN
Classifier: Development Status :: 4 - Beta
Classifier: Intended Audience :: Developers
Classifier: License :: Other/Proprietary License
Classifier: Operating System :: OS Independent
Classifier: Programming Language :: Python
Requires-Python: >=3
Requires-Dist: ruamel.std.pathlib
